polaris_cli/__init__.py
polaris_cli/main.py
polaris_cli/auth/__init__.py
polaris_cli/auth/token_manager.py
polaris_cli/commands/__init__.py
polaris_cli/commands/auth_commands.py
polaris_cli/commands/billing_commands.py
polaris_cli/commands/cluster_commands.py
polaris_cli/commands/config_commands.py
polaris_cli/commands/instance_commands.py
polaris_cli/commands/resource_commands.py
polaris_cli/commands/ssh_commands.py
polaris_cli/commands/status_commands.py
polaris_cli/commands/template_commands.py
polaris_cli/config/__init__.py
polaris_cli/config/manager.py
polaris_cli/data/__init__.py
polaris_cli/data/dummy_data.py
polaris_cli/ui/__init__.py
polaris_cli/ui/banner.py
polaris_cli/ui/tables.py
polaris_cli/utils/__init__.py
polaris_cli/utils/api_client.py
polaris_cli/utils/exceptions.py
polaris_cli-1.0.1.dist-info/licenses/LICENSE
polaris_cli-1.0.1.dist-info/METADATA
polaris_cli-1.0.1.dist-info/WHEEL
polaris_cli-1.0.1.dist-info/entry_points.txt
polaris_cli-1.0.1.dist-info/top_level.txt
polaris_cli-1.0.1.dist-info/RECORD
