Metadata-Version: 2.4
Name: polaris-cli
Version: 1.0.1
Summary: A beautiful and powerful cloud resource management CLI for Polaris Cloud
Author-email: Polaris Team <team@polaris.dev>
License-Expression: MIT
Project-URL: Homepage, https://github.com/polaris-cloud/polaris-cli
Project-URL: Bug Reports, https://github.com/polaris-cloud/polaris-cli/issues
Project-URL: Source, https://github.com/polaris-cloud/polaris-cli
Project-URL: Documentation, https://docs.polaris.cloud/cli
Keywords: cloud,cli,infrastructure,polaris,resource-management
Classifier: Development Status :: 4 - Beta
Classifier: Environment :: Console
Classifier: Intended Audience :: Developers
Classifier: Intended Audience :: System Administrators
Classifier: Operating System :: OS Independent
Classifier: Programming Language :: Python :: 3
Classifier: Programming Language :: Python :: 3.9
Classifier: Programming Language :: Python :: 3.10
Classifier: Programming Language :: Python :: 3.11
Classifier: Programming Language :: Python :: 3.12
Classifier: Topic :: System :: Systems Administration
Classifier: Topic :: Utilities
Requires-Python: >=3.9
License-File: LICENSE
Requires-Dist: typer>=0.9.0
Requires-Dist: rich>=13.7.0
Requires-Dist: requests>=2.32.0
Requires-Dist: pydantic>=2.5.0
Requires-Dist: keyring>=24.0.0
Requires-Dist: python-dateutil>=2.8.0
Requires-Dist: pyfiglet>=1.0.0
Requires-Dist: colorama>=0.4.6
Requires-Dist: alive-progress>=3.1.0
Provides-Extra: dev
Requires-Dist: pytest>=7.4.0; extra == "dev"
Requires-Dist: black>=23.0.0; extra == "dev"
Requires-Dist: flake8>=6.0.0; extra == "dev"
Requires-Dist: mypy>=1.5.0; extra == "dev"
Requires-Dist: build>=0.10.0; extra == "dev"
Requires-Dist: twine>=4.0.0; extra == "dev"
Dynamic: license-file
